jprinter/__init__.py
jprinter/builtins.py
jprinter/coloring.py
jprinter/core.py
jprinter/jp.py
jprinter/jprint.py
jprinter-0.1.1.dist-info/METADATA
jprinter-0.1.1.dist-info/WHEEL
jprinter-0.1.1.dist-info/top_level.txt
jprinter-0.1.1.dist-info/RECORD
