Metadata-Version: 2.1
Name: jprinter
Version: 0.1.1
Summary: A Python library for enhanced printing and debugging.
Home-page: https://github.com/OE-LUCIFER/JPRINT
Author: Abhay Koul
Author-email: helpingai5@gmail.com
License: Apache 2.0
Project-URL: Source, https://github.com/OE-LUCIFER/JPRINT
Project-URL: Bug Reports, https://github.com/OE-LUCIFER/JPRINT/issues
Keywords: debugging print logging development
Classifier: Development Status :: 3 - Alpha
Classifier: Intended Audience :: Developers
Classifier: Topic :: Software Development :: Debuggers
Classifier: License :: OSI Approved :: Apache Software License
Classifier: Programming Language :: Python :: 3
Classifier: Programming Language :: Python :: 3.7
Classifier: Programming Language :: Python :: 3.8
Classifier: Programming Language :: Python :: 3.9
Classifier: Programming Language :: Python :: 3.10
Classifier: Programming Language :: Python :: 3.11
Classifier: Programming Language :: Python :: 3.12
Requires-Python: >=3.7
Requires-Dist: colorama
Requires-Dist: executing
Requires-Dist: pygments
